{
	"backtrace" : 0,
	"backtraceGraph" : 
	{
		"commands" : [],
		"files" : 
		[
			"libxml/calibration/CMakeLists.txt"
		],
		"nodes" : 
		[
			{
				"file" : 0
			}
		]
	},
	"codemodelVersion" : 
	{
		"major" : 2,
		"minor" : 10
	},
	"dependencies" : 
	[
		{
			"id" : "calibration_autogen_timestamp_deps::@a0758e5992c0ef5137ee"
		}
	],
	"folder" : 
	{
		"name" : "QtInternalTargets"
	},
	"id" : "calibration_autogen::@a0758e5992c0ef5137ee",
	"isGeneratorProvided" : true,
	"name" : "calibration_autogen",
	"orderDependencies" : 
	[
		{
			"id" : "Qt6::moc::@6890427a1f51a3e7e1df"
		},
		{
			"id" : "Qt6::uic::@6890427a1f51a3e7e1df"
		},
		{
			"id" : "calibration_autogen_timestamp_deps::@a0758e5992c0ef5137ee"
		}
	],
	"paths" : 
	{
		"build" : "libxml/calibration",
		"source" : "libxml/calibration"
	},
	"sourceGroups" : 
	[
		{
			"name" : "",
			"sourceIndexes" : 
			[
				0
			]
		},
		{
			"name" : "CMake Rules",
			"sourceIndexes" : 
			[
				1,
				2
			]
		}
	],
	"sources" : 
	[
		{
			"backtrace" : 0,
			"isGenerated" : true,
			"path" : "out/build/Clang 19.1.7 x86_64-pc-linux-gnu/libxml/calibration/CMakeFiles/calibration_autogen",
			"sourceGroupIndex" : 0
		},
		{
			"backtrace" : 0,
			"isGenerated" : true,
			"path" : "out/build/Clang 19.1.7 x86_64-pc-linux-gnu/libxml/calibration/CMakeFiles/calibration_autogen.rule",
			"sourceGroupIndex" : 1
		},
		{
			"backtrace" : 0,
			"isGenerated" : true,
			"path" : "out/build/Clang 19.1.7 x86_64-pc-linux-gnu/libxml/calibration/calibration_autogen/timestamp.rule",
			"sourceGroupIndex" : 1
		}
	],
	"type" : "UTILITY"
}
